MANIFEST.in
README
README.rst
setup.cfg
setup.py
fabric/__init__.py
fabric/contrib/__init__.py
fabric/contrib/naked.py
fabric_naked.egg-info/PKG-INFO
fabric_naked.egg-info/SOURCES.txt
fabric_naked.egg-info/dependency_links.txt
fabric_naked.egg-info/namespace_packages.txt
fabric_naked.egg-info/not-zip-safe
fabric_naked.egg-info/requires.txt
fabric_naked.egg-info/top_level.txt