Metadata-Version: 1.0
Name: fabric-naked
Version: 0.0.1
Summary: execute your nakedo work procedure by fabric
Home-page: https://github.com/yuokada/fabric-naked
Author: Yukihiro Okada
Author-email: callistoiv+pypi@gmail.com
License: BSD
Platform: UNKNOWN
Classifier: License :: OSI Approved :: BSD License
Classifier: Programming Language :: Python :: 2.6
Classifier: Programming Language :: Python :: 2.7
Classifier: Environment :: Console
Classifier: Intended Audience :: Developers
Classifier: Intended Audience :: System Administrators
Classifier: Operating System :: MacOS :: MacOS X
Classifier: Operating System :: POSIX
Classifier: Operating System :: Unix
Classifier: Programming Language :: Python
Classifier: Topic :: Software Development
Classifier: Topic :: Software Development :: Build Tools
Classifier: Topic :: Software Development :: Libraries
Classifier: Topic :: Software Development :: Libraries :: Python Modules
Classifier: Topic :: System :: Clustering
Classifier: Topic :: System :: Software Distribution
Classifier: Topic :: System :: Systems Administration
